bufrtools/__init__.py
bufrtools/encode_animal_tag.py
bufrtools/decoding/__init__.py
bufrtools/encoding/__init__.py
bufrtools/encoding/bufr.py
bufrtools/encoding/wildlife_computers.py
bufrtools/tables/__init__.py
bufrtools/tables/data/BUFRCREX_CodeFlag_en_01.csv
bufrtools/tables/data/BUFRCREX_CodeFlag_en_02.csv
bufrtools/tables/data/BUFRCREX_CodeFlag_en_03.csv
bufrtools/tables/data/BUFRCREX_CodeFlag_en_04.csv
bufrtools/tables/data/BUFRCREX_CodeFlag_en_05.csv
bufrtools/tables/data/BUFRCREX_CodeFlag_en_08.csv
bufrtools/tables/data/BUFRCREX_CodeFlag_en_10.csv
bufrtools/tables/data/BUFRCREX_CodeFlag_en_11.csv
bufrtools/tables/data/BUFRCREX_CodeFlag_en_13.csv
bufrtools/tables/data/BUFRCREX_CodeFlag_en_15.csv
bufrtools/tables/data/BUFRCREX_CodeFlag_en_19.csv
bufrtools/tables/data/BUFRCREX_CodeFlag_en_20.csv
bufrtools/tables/data/BUFRCREX_CodeFlag_en_21.csv
bufrtools/tables/data/BUFRCREX_CodeFlag_en_22.csv
bufrtools/tables/data/BUFRCREX_CodeFlag_en_23.csv
bufrtools/tables/data/BUFRCREX_CodeFlag_en_24.csv
bufrtools/tables/data/BUFRCREX_CodeFlag_en_25.csv
bufrtools/tables/data/BUFRCREX_CodeFlag_en_26.csv
bufrtools/tables/data/BUFRCREX_CodeFlag_en_29.csv
bufrtools/tables/data/BUFRCREX_CodeFlag_en_30.csv
bufrtools/tables/data/BUFRCREX_CodeFlag_en_31.csv
bufrtools/tables/data/BUFRCREX_CodeFlag_en_33.csv
bufrtools/tables/data/BUFRCREX_CodeFlag_en_35.csv
bufrtools/tables/data/BUFRCREX_CodeFlag_en_40.csv
bufrtools/tables/data/BUFRCREX_CodeFlag_en_42.csv
bufrtools/tables/data/BUFRCREX_TableB_en_00.csv
bufrtools/tables/data/BUFRCREX_TableB_en_01.csv
bufrtools/tables/data/BUFRCREX_TableB_en_02.csv
bufrtools/tables/data/BUFRCREX_TableB_en_03.csv
bufrtools/tables/data/BUFRCREX_TableB_en_04.csv
bufrtools/tables/data/BUFRCREX_TableB_en_05.csv
bufrtools/tables/data/BUFRCREX_TableB_en_06.csv
bufrtools/tables/data/BUFRCREX_TableB_en_07.csv
bufrtools/tables/data/BUFRCREX_TableB_en_08.csv
bufrtools/tables/data/BUFRCREX_TableB_en_10.csv
bufrtools/tables/data/BUFRCREX_TableB_en_11.csv
bufrtools-1.1.4.dist-info/LICENSE.txt
bufrtools-1.1.4.dist-info/METADATA
bufrtools-1.1.4.dist-info/WHEEL
bufrtools-1.1.4.dist-info/top_level.txt
bufrtools-1.1.4.dist-info/RECORD
