Metadata-Version: 2.1
Name: bufrtools
Version: 1.1.4
Summary: A suite of tools for working with BUFR
Home-page: https://github.com/axiom-data-science/bufrtools
Author: Luke Campbell
Author-email: luke@axds.co
License-File: LICENSE.txt
Requires-Dist: cftime
Requires-Dist: pandas
Requires-Dist: pocean-core (>=1.9.3)
Requires-Dist: pyarrow
Requires-Dist: pyyaml
